{"assets":{"69ED4DCFDC5D6F4B94743A1C34E6CFEF":{"type":"texture","index":1,"assetRequest":{"type":"slide","state":"incoming","slide":"0DE016D1-8935-4ECC-9FE7-AA69755B8A1A"},"url":{"web":"assets/63A15AA9-4A15-43A4-B141-DF79CE59D98A.svgmap"},"width":1920,"height":1080},"530F64370A4F68C3B659A1B1F2B91B46":{"type":"texture","index":0,"assetRequest":{"type":"slide","state":"outgoing","slide":"63A15AA9-4A15-43A4-B141-DF79CE59D98A"},"url":{"web":"assets/63A15AA9-4A15-43A4-B141-DF79CE59D98A.svgmap"},"width":1920,"height":1080}},"events":[{"effects":[{"beginTime":0,"baseLayer":{"animations":[],"initialState":{"affineTransform":[1,0,0,1,0,0],"masksToBounds":false,"rotation":0,"scale":1,"position":{"pointX":960,"pointY":540},"width":1920,"sublayerTransform":[1,0,0,0,0,1,0,0,0,0,1,0,0,0,0,1],"contentsRect":{"y":0,"x":0,"width":1,"height":1},"opacity":1,"edgeAntialiasingMask":251658240,"height":1080,"hidden":false,"anchorPoint":{"pointX":0.5,"pointY":0.5}},"objectID":"0","layers":[{"animations":[],"initialState":{"affineTransform":[1,0,0,1,0,0],"masksToBounds":false,"rotation":0,"scale":1,"position":{"pointX":960,"pointY":540},"width":1920,"sublayerTransform":[1,0,0,0,0,1,0,0,0,0,1,-0.0003500791246677598,0,0,0,1],"contentsRect":{"y":0,"x":0,"width":1,"height":1},"opacity":1,"edgeAntialiasingMask":251658240,"height":1080,"hidden":false,"anchorPoint":{"pointX":0.5,"pointY":0.5}},"layers":[{"animations":[],"layers":[],"texturedRectangle":{"isBackgroundTexture":false,"singleTextureOpacity":1,"textureType":0,"textBaseline":0,"textXHeight":0,"isVerticalText":false},"initialState":{"affineTransform":[1,0,0,1,0,0],"masksToBounds":false,"rotation":0,"scale":1,"position":{"pointX":960,"pointY":540},"width":1920,"sublayerTransform":[1,0,0,0,0,1,0,0,0,0,1,0,0,0,0,1],"contentsRect":{"y":0,"x":0,"width":1,"height":1},"opacity":1,"edgeAntialiasingMask":0,"height":1080,"hidden":false,"anchorPoint":{"pointX":0.5,"pointY":0.5}},"texture":"69ED4DCFDC5D6F4B94743A1C34E6CFEF"},{"animations":[{"timeOffset":0,"from":{"scalar":false},"beginTime":0,"repeatCount":0,"fillMode":"both","property":"hidden","autoreverses":false,"duration":0.01,"to":{"scalar":true}}],"layers":[],"texturedRectangle":{"isBackgroundTexture":false,"singleTextureOpacity":1,"textureType":0,"textBaseline":0,"textXHeight":0,"isVerticalText":false},"initialState":{"affineTransform":[1,0,0,1,0,0],"masksToBounds":false,"rotation":0,"scale":1,"position":{"pointX":960,"pointY":540},"width":1920,"sublayerTransform":[1,0,0,0,0,1,0,0,0,0,1,0,0,0,0,1],"contentsRect":{"y":0,"x":0,"width":1,"height":1},"opacity":1,"edgeAntialiasingMask":0,"height":1080,"hidden":false,"anchorPoint":{"pointX":0.5,"pointY":0.5}},"texture":"530F64370A4F68C3B659A1B1F2B91B46"}]}]},"effects":[],"duration":0.01,"type":"transition","name":"none","objectID":"0"}],"automaticPlay":false,"hyperlinks":[],"accessibility":[{"text":"Screen Shot 2016-09-16 at 8.59.05 AM.png","targetRectangle":{"y":760.3015747070312,"x":188.5861053466797,"width":881.1784057617188,"height":313.19970703125}},{"text":"School of Geosciences","targetRectangle":{"y":1039.375854492188,"x":1701.960205078125,"width":199.053955078125,"height":25}},{"text":"Screen Shot 2016-09-16 at 8.59.21 AM.png","targetRectangle":{"y":427.7034301757812,"x":152.8845825195312,"width":952.5814819335938,"height":295.3489379882812}},{"text":"Screen Shot 2016-09-16 at 9.04.03 AM.png","targetRectangle":{"y":805.5934448242188,"x":1095.731567382812,"width":681.65380859375,"height":222.6160430908203}},{"text":"Descending regressive","targetRectangle":{"y":630.1710817813873,"x":82.43274593353271,"width":430,"height":55}},{"text":"Transgressive","targetRectangle":{"y":931.5814821720123,"x":166.7100777626038,"width":261.4453125,"height":55}},{"text":"Ascending regressive","targetRectangle":{"y":326.9741823673248,"x":95.41125202178955,"width":404.04296875,"height":55}},{"text":"Screen Shot 2016-09-12 at 3.25.48 PM.png","targetRectangle":{"y":362.4153137207031,"x":1283.071559906006,"width":641.09375,"height":125.4197785865108}},{"text":"Screen Shot 2016-09-16 at 9.03.41 AM.png","targetRectangle":{"y":524.319091796875,"x":1076.952270507812,"width":769.6516723632812,"height":284.853271484375}},{"text":"Screen Shot 2016-09-12 at 3.25.48 PM.png","targetRectangle":{"y":24.28351545333862,"x":1391.601318359375,"width":612.723859605605,"height":547.09375}},{"text":"Screen Shot 2016-09-16 at 8.59.27 AM.png","targetRectangle":{"y":157.6497344970703,"x":154.5073852539062,"width":949.3358764648438,"height":295.3489379882812}},{"text":"Trajectory analysis","targetRectangle":{"y":31.72067832946777,"x":567.2138671875,"width":785.572265625,"height":115}}],"baseLayer":{"animations":[],"initialState":{"affineTransform":[1,0,0,1,0,0],"masksToBounds":false,"rotation":0,"scale":1,"position":{"pointX":960,"pointY":540},"width":1920,"sublayerTransform":[1,0,0,0,0,1,0,0,0,0,1,0,0,0,0,1],"contentsRect":{"y":0,"x":0,"width":1,"height":1},"opacity":1,"edgeAntialiasingMask":251658240,"height":1080,"hidden":false,"anchorPoint":{"pointX":0.5,"pointY":0.5}},"objectID":"0","layers":[{"animations":[],"initialState":{"affineTransform":[1,0,0,1,0,0],"masksToBounds":false,"rotation":0,"scale":1,"position":{"pointX":960,"pointY":540},"width":1920,"sublayerTransform":[1,0,0,0,0,1,0,0,0,0,1,-0.0003500791246677598,0,0,0,1],"contentsRect":{"y":0,"x":0,"width":1,"height":1},"opacity":1,"edgeAntialiasingMask":251658240,"height":1080,"hidden":false,"anchorPoint":{"pointX":0.5,"pointY":0.5}},"layers":[{"animations":[],"layers":[],"texturedRectangle":{"isBackgroundTexture":false,"singleTextureOpacity":1,"textureType":0,"textBaseline":0,"textXHeight":0,"isVerticalText":false},"initialState":{"affineTransform":[1,0,0,1,0,0],"masksToBounds":false,"rotation":0,"scale":1,"position":{"pointX":960,"pointY":540},"width":1920,"sublayerTransform":[1,0,0,0,0,1,0,0,0,0,1,0,0,0,0,1],"contentsRect":{"y":0,"x":0,"width":1,"height":1},"opacity":1,"edgeAntialiasingMask":0,"height":1080,"hidden":false,"anchorPoint":{"pointX":0.5,"pointY":0.5}},"texture":"530F64370A4F68C3B659A1B1F2B91B46"}]}]}}]}